pheval_semphen/__init__.py
pheval_semphen/runner.py
pheval_semphen/semphen.py
pheval_semphen/test_configs/config.yaml
pheval_semphen-0.0.0.dist-info/LICENSE
pheval_semphen-0.0.0.dist-info/METADATA
pheval_semphen-0.0.0.dist-info/WHEEL
pheval_semphen-0.0.0.dist-info/entry_points.txt
pheval_semphen-0.0.0.dist-info/RECORD
