Metadata-Version: 2.1
Name: pheval_semphen
Version: 0.0.0
Summary: Pheval runner for semsimian + phenio db + MONDO (semphen) for disease prioritization via phenotype similarities
Author: Aaron Odell
Author-email: aaron@tislab.org
Requires-Python: >=3.9,<4.0
Classifier: Programming Language :: Python :: 3
Classifier: Programming Language :: Python :: 3.9
Classifier: Programming Language :: Python :: 3.10
Classifier: Programming Language :: Python :: 3.11
Classifier: Programming Language :: Python :: 3.12
Classifier: Programming Language :: Python :: 3.13
Requires-Dist: click
Requires-Dist: importlib-metadata (>=8.2.0)
Requires-Dist: pheval (>=0.3.9,<0.4.0)
Requires-Dist: semsimian (>=0.2.17)
